tmgtoolkit/__init__.py
tmgtoolkit/constants.py
tmgtoolkit/plotting.py
tmgtoolkit/spm.py
tmgtoolkit/time_series.py
tmgtoolkit/tmgio.py
tmgtoolkit-0.1.5.dist-info/LICENSE.md
tmgtoolkit-0.1.5.dist-info/METADATA
tmgtoolkit-0.1.5.dist-info/WHEEL
tmgtoolkit-0.1.5.dist-info/top_level.txt
tmgtoolkit-0.1.5.dist-info/RECORD
