Metadata-Version: 2.1
Name: tmgtoolkit
Version: 0.1.5
Summary: Time series analysis of tensiomyography (TMG) data
Home-page: https://github.com/ejmastnak/tmgtoolkit
Author: Elijan Mastnak
Author-email: admin@ejmastnak.com
Project-URL: Bug Tracker, https://github.com/ejmastnak/tmgtoolkit/issues
Classifier: Programming Language :: Python :: 3
Classifier: License :: OSI Approved :: GNU General Public License v3 (GPLv3)
Classifier: Operating System :: OS Independent
Requires-Python: >=3.9
License-File: LICENSE.md
Requires-Dist: spm1d >=0.4
Requires-Dist: numpy
Requires-Dist: scipy
Requires-Dist: matplotlib
Requires-Dist: pandas
Requires-Dist: openpyxl
